__init__.py
server.py
iflow_mcp_ip2location_ip2locationio-0.1.0.dist-info/licenses/LICENSE.TXT
iflow_mcp_ip2location_ip2locationio-0.1.0.dist-info/METADATA
iflow_mcp_ip2location_ip2locationio-0.1.0.dist-info/WHEEL
iflow_mcp_ip2location_ip2locationio-0.1.0.dist-info/entry_points.txt
iflow_mcp_ip2location_ip2locationio-0.1.0.dist-info/top_level.txt
iflow_mcp_ip2location_ip2locationio-0.1.0.dist-info/RECORD
