Metadata-Version: 2.4
Name: iflow-mcp_ip2location_ip2locationio
Version: 0.1.0
Summary: Add your description here
Requires-Python: >=3.13
License-File: LICENSE.TXT
Requires-Dist: httpx>=0.28.1
Requires-Dist: mcp[cli]>=1.9.4
Dynamic: license-file
